adaptors/InputAdaptorHandler.py
adaptors/OutputAdaptorHandler.py
adaptors/__init__.py
adaptors/input/AbstractInputAdaptor.py
adaptors/input/InputCSVFileAdaptor.py
adaptors/input/InputHTMLFileAdaptor.py
adaptors/input/InputJSONFileAdaptor.py
adaptors/input/InputJSONLFileAdaptor.py
adaptors/input/InputTextFileAdaptor.py
adaptors/input/InputURLAdaptor.py
adaptors/input/__init__.py
adaptors/output/AbstractOutputAdaptor.py
adaptors/output/OutputCSVFileAdaptor.py
adaptors/output/OutputHTMLFileAdaptor.py
adaptors/output/OutputJSONFileAdaptor.py
adaptors/output/OutputJSONLFileAdaptor.py
adaptors/output/OutputTextFileAdaptor.py
adaptors/output/__init__.py
pysmartshell/AbstractAction.py
pysmartshell/AbstractActionWithConfiguration.py
pysmartshell/ActionLoader.py
pysmartshell/ActionsLoader.py
pysmartshell/ArgParser.py
pysmartshell/Argument.py
pysmartshell/ConfigurationHandler.py
pysmartshell/__init__.py
pysmartshell/adaptors/InputAdaptorHandler.py
pysmartshell/adaptors/OutputAdaptorHandler.py
pysmartshell/adaptors/__init__.py
pysmartshell/adaptors/input/AbstractInputAdaptor.py
pysmartshell/adaptors/input/InputCSVFileAdaptor.py
pysmartshell/adaptors/input/InputHTMLFileAdaptor.py
pysmartshell/adaptors/input/InputJSONFileAdaptor.py
pysmartshell/adaptors/input/InputJSONLFileAdaptor.py
pysmartshell/adaptors/input/InputTextFileAdaptor.py
pysmartshell/adaptors/input/InputURLAdaptor.py
pysmartshell/adaptors/input/__init__.py
pysmartshell/adaptors/output/AbstractOutputAdaptor.py
pysmartshell/adaptors/output/OutputCSVFileAdaptor.py
pysmartshell/adaptors/output/OutputHTMLFileAdaptor.py
pysmartshell/adaptors/output/OutputJSONFileAdaptor.py
pysmartshell/adaptors/output/OutputJSONLFileAdaptor.py
pysmartshell/adaptors/output/OutputTextFileAdaptor.py
pysmartshell/adaptors/output/__init__.py
pysmartshell/tests/__init__.py
PySmartShell-0.0.5.dist-info/LICENCE
PySmartShell-0.0.5.dist-info/METADATA
PySmartShell-0.0.5.dist-info/WHEEL
PySmartShell-0.0.5.dist-info/top_level.txt
PySmartShell-0.0.5.dist-info/RECORD
